{
"type": "FeatureCollection",
"name": "bcnisd",
"crs": { "type": "name", "properties": { "name": "urn:ogc:def:crs:OGC:1.3:CRS84" } },
"xy_coordinate_resolution": 1e-15,
"features": [
{ "type": "Feature", "properties": { "id": 68, "inspireid": "FR000001124400001", "posacc": 0.4, "objnam": "Lavardin", "nobjnm": null, "inform": null, "ninfom": null, "numald": "1700318", "persta": null, "perend": null, "condtn": null, "convis": 2, "bcnshp": 3, "colour": "2,3,2", "colpat": "1", "height": 19.0, "verlen": 21.0, "status": null, "aisatn": "", "daymar": "", "topmar": "", "fogsig": "", "radsta": "", "rtpbcn": "", "rdosta": "", "sistat": "", "sistaw": "", "lights": "FR000004763800001" }, "geometry": { "type": "Point", "coordinates": [ -1.2419934, 46.1347895 ] } }
]
}
